LICENSE
MANIFEST.in
README.md
pyproject.toml
setup.py
version.txt
tests/__init__.py
tests/full_numerai_test.py
tests/numerai_test.py
tests/test_comparison_lightgbm.py
tests/test_feature_importance.py
tests/test_fit_predict_corr.py
tests/test_invariant.py
tests/test_multiclass.py
tests/test_random_state.py
tests/test_warm_start.py
warpgbm/__init__.py
warpgbm/core.py
warpgbm/metrics.py
warpgbm.egg-info/PKG-INFO
warpgbm.egg-info/SOURCES.txt
warpgbm.egg-info/dependency_links.txt
warpgbm.egg-info/requires.txt
warpgbm.egg-info/top_level.txt
warpgbm/cuda/__init__.py
warpgbm/cuda/best_split_kernel.cu
warpgbm/cuda/binner.cu
warpgbm/cuda/histogram_kernel.cu
warpgbm/cuda/node_kernel.cpp
warpgbm/cuda/predict.cu