Metadata-Version: 2.4
Name: warpgbm
Version: 2.2.0
Summary: A fast GPU-accelerated Gradient Boosted Decision Tree library with PyTorch + CUDA
License:                     GNU GENERAL PUBLIC LICENSE
Requires-Python: >=3.8
License-File: LICENSE
Requires-Dist: torch
Requires-Dist: numpy
Requires-Dist: tqdm
Requires-Dist: scikit-learn
Dynamic: license-file
